{
  "Title": "The Naked Gun 2\u00BD: The Smell of Fear",
  "FullTitle": "The Naked Gun 2\u00BD: The Smell of Fear (1991)",
  "Slug": "the-naked-gun-2-the-smell-of-fear-1991",
  "Type": "Movie",
  "Year": 1991,
  "ImageUrl": "Movie/the-naked-gun-2-the-smell-of-fear-1991/cover.jpg",
  "ExternalIds": {
    "Tmdb": "37137",
    "Imdb": "tt0102510",
    "Tvdb": null
  },
  "Plot": "Lieutenant Frank Drebbin returns to save the day once again. This time he\u0027s out to foil the \u0022big boys\u0022 in the energy business. A top scientist (Dr. Mainheimer) is about to publish his report on energy supply for the future. Things don\u0027t look good for the traditional suppliers; oil, coal, and nuclear. To save their industries, the suppliers kidnap Mainheimer and replace him with a decoy with a more favorable report. Jane, the doctor\u0027s secretary, is Drebin\u0027s old flame. Their passionate love affair is thus rekindled.",
  "Tagline": "If you see only one movie this year...you ought to get out more often.",
  "Directors": "David Zucker",
  "Writers": "Jim Abrahams, David Zucker, Jerry Zucker",
  "Stars": "Leslie Nielsen, Priscilla Presley, George Kennedy",
  "Genres": "Comedy, Crime",
  "RuntimeMinutes": 85,
  "Runtime": "1h 25min",
  "ContentRating": "PG-13"
}