{
  "backdrop_path": "/oGNExSpm08lTWoLo6FmZlGDAimD.jpg",
  "created_by": [
    {
      "id": 9156,
      "credit_id": "525972df760ee34661a496f3",
      "name": "Andrew Davies",
      "gender": 2,
      "profile_path": "/gOxUTVdqNinS2KQvEyIAMKPKt6s.jpg"
    }
  ],
  "credits": {
    "cast": [
      {
        "character": "Harry Selfridge",
        "credit_id": "525972dc760ee34661a495d9",
        "id": 12799,
        "name": "Jeremy Piven",
        "profile_path": "/dPCFGmNhrF3niEJMPIbC1fiIqyI.jpg",
        "gender": 2
      },
      {
        "character": "Lady Mae Loxley",
        "credit_id": "527f560c760ee34ce32382bc",
        "id": 543632,
        "name": "Katherine Kelly",
        "order": 2,
        "profile_path": "/gh8uNkRvuC6cHpnXKtaT2iKg0Ht.jpg",
        "gender": 1
      },
      {
        "character": "Miss Mardle",
        "credit_id": "527f56e4760ee33eab36e6b8",
        "id": 199522,
        "name": "Amanda Abbington",
        "order": 3,
        "profile_path": "/diashQMD26rrZOmj342EK8a6EaQ.jpg",
        "gender": 1
      },
      {
        "character": "Mr. Crabb",
        "credit_id": "525972dc760ee34661a49623",
        "id": 5319,
        "name": "Ron Cook",
        "order": 4,
        "profile_path": "/bYJ2x9FfQobon2Iai5CvoLgv1U5.jpg",
        "gender": 2
      },
      {
        "character": "Kitty",
        "credit_id": "525972dd760ee34661a49673",
        "id": 137411,
        "name": "Amy Beth Hayes",
        "order": 8,
        "profile_path": "/qLc2768NjxcRUNRuTomiVAgi35S.jpg",
        "gender": 1
      },
      {
        "character": "Mr. Grove",
        "credit_id": "525972dd760ee34661a49687",
        "id": 43034,
        "name": "Tom Goodman-Hill",
        "order": 9,
        "profile_path": "/2rC1qhYmJiuk3iY15Ms7VLau6XD.jpg",
        "gender": 2
      },
      {
        "character": "Miss Blenkinsop",
        "credit_id": "525972dd760ee34661a4969b",
        "id": 1232673,
        "name": "Deborah Cornelius",
        "order": 10,
        "gender": 1
      },
      {
        "character": "Lois Selfridge",
        "credit_id": "525972de760ee34661a496c6",
        "id": 42567,
        "name": "Kika Markham",
        "order": 12,
        "profile_path": "/lIIQiLBkpsZbQGPHXqDpmLLd18F.jpg",
        "gender": 1
      },
      {
        "character": "Victor",
        "credit_id": "525972df760ee34661a496e1",
        "id": 589651,
        "name": "Trystan Gravelle",
        "order": 13,
        "profile_path": "/2MnUKu2UbHpkA4Ne5HP8XOL0KkB.jpg",
        "gender": 2
      },
      {
        "character": "Fraser",
        "credit_id": "5cdc4dd4c3a3684a97c92aac",
        "id": 185403,
        "name": "Malcolm Rennie",
        "order": 500,
        "profile_path": "/aMsxW3ACaT8CayNqCnorKKSmhHz.jpg",
        "gender": 2
      }
    ],
    "crew": []
  },
  "episode_run_time": [
    60
  ],
  "external_ids": {
    "imdb_id": "tt2310212",
    "tvdb_id": "261633",
    "freebase_mid": "/m/0p3p79d",
    "tvrage_id": "33287"
  },
  "first_air_date": "2013-01-06T00:00:00-08:00",
  "genres": [
    {
      "id": 18,
      "name": "Drama"
    }
  ],
  "homepage": "http://www.itv.com/hub/mr-selfridge",
  "id": 46643,
  "images": {
    "backdrops": [
      {
        "aspect_ratio": 1.778,
        "file_path": "/oGNExSpm08lTWoLo6FmZlGDAimD.jpg",
        "height": 1080,
        "width": 1920
      }
    ],
    "posters": [
      {
        "aspect_ratio": 0.667,
        "file_path": "/pm4wMixNf5QPYQbdt0tnkbhmQvW.jpg",
        "height": 1500,
        "iso_639_1": "en",
        "vote_average": 5.312,
        "vote_count": 1,
        "width": 1000
      },
      {
        "aspect_ratio": 0.667,
        "file_path": "/nvJaLr84qsMZP7HhrnjUpsuUsE4.jpg",
        "height": 900,
        "iso_639_1": "en",
        "vote_average": 5.172,
        "vote_count": 1,
        "width": 600
      }
    ]
  },
  "keywords": {
    "results": [
      {
        "id": 212,
        "name": "london, england"
      },
      {
        "id": 2081,
        "name": "department store"
      },
      {
        "id": 12995,
        "name": "historical fiction"
      },
      {
        "id": 15060,
        "name": "period drama"
      },
      {
        "id": 181087,
        "name": "american in the uk"
      },
      {
        "id": 195013,
        "name": "costume drama"
      },
      {
        "id": 208202,
        "name": "shopgirl"
      }
    ]
  },
  "languages": [
    "en"
  ],
  "last_air_date": "2016-03-11T00:00:00-08:00",
  "last_episode_to_air": {
    "air_date": "2016-03-11T00:00:00-08:00",
    "name": "Episode 10",
    "overview": "Harry\u0027s judgement, Whiteley\u0027s and even Lady Mae\u0027s love life are now all under the spotlight of a tabloid frenzy. Jimmy\u0027s final act has Harry reeling and the retail mogul retreats from the publicity for the sanctuary of home. Mae, now at the end of her tether, contemplates her future in London. The threat of a trade embargo imposed by Hardcastle sees acting boss Gordon backed into a corner, and Harry called to account.",
    "production_code": "",
    "still_path": "/y8DqwpZX7RI3YkS4CxxsId1SOGp.jpg",
    "vote_average": 9,
    "vote_count": 1,
    "id": 1156251,
    "season_number": 4,
    "episode_number": 10
  },
  "name": "Mr Selfridge",
  "networks": [
    {
      "logo_path": "/5Rmw4ViYcjW14PCdOyjsue9eK99.png",
      "id": 9,
      "name": "ITV",
      "origin_country": "GB"
    },
    {
      "logo_path": "/hp2Fs7AIdsMlEjiDUC1V8Ows2jM.png",
      "id": 14,
      "name": "PBS",
      "origin_country": "US"
    }
  ],
  "number_of_episodes": 40,
  "number_of_seasons": 4,
  "original_language": "en",
  "original_name": "Mr Selfridge",
  "origin_country": [
    "GB"
  ],
  "overview": "Mr. Selfridge recounts the real life story of the flamboyant and visionary American founder of Selfridge\u0027s, London\u0027s lavish department store. Set in 1909 London, when women were reveling in a new sense of freedom and modernity, it follows Harry Gordon Selfridge (\u0027Mile a Minute Harry\u0027), a man with a mission to make shopping as thrilling as sex. Pioneering and reckless, with an almost manic energy, Harry created a theater of retail where any topic or trend that was new, exciting, entertaining - or just eccentric - was showcased.",
  "popularity": 9.284,
  "poster_path": "/pm4wMixNf5QPYQbdt0tnkbhmQvW.jpg",
  "production_companies": [
    {
      "id": 24546,
      "name": "ITV Studios",
      "logo_path": "/AffgIsVKcudKagSu3MV3phsV5Vw.png",
      "origin_country": "GB"
    },
    {
      "id": 24790,
      "name": "Masterpiece",
      "logo_path": "/hXkXnEb2eofddcX7C1Oms81ERAZ.png",
      "origin_country": "US"
    }
  ],
  "seasons": [
    {
      "air_date": "2013-11-03T00:00:00-07:00",
      "episode_count": 1,
      "id": 54811,
      "name": "Specials",
      "overview": ""
    },
    {
      "air_date": "2013-01-06T00:00:00-08:00",
      "episode_count": 10,
      "id": 54812,
      "name": "Season 1",
      "overview": "",
      "poster_path": "/pm4wMixNf5QPYQbdt0tnkbhmQvW.jpg",
      "season_number": 1
    },
    {
      "air_date": "2014-01-19T00:00:00-08:00",
      "episode_count": 10,
      "id": 63312,
      "name": "Season 2",
      "overview": "",
      "poster_path": "/sugBbAsBbPExSukvV0naHesJ6p0.jpg",
      "season_number": 2
    },
    {
      "air_date": "2015-01-25T00:00:00-08:00",
      "episode_count": 10,
      "id": 63313,
      "name": "Season 3",
      "overview": "It is now 1919 and the Great War is over.",
      "poster_path": "/vTuHH73bciOGI1SQs8pm96SQD9t.jpg",
      "season_number": 3
    },
    {
      "air_date": "2016-01-08T00:00:00-08:00",
      "episode_count": 10,
      "id": 72888,
      "name": "Season 4",
      "overview": "",
      "poster_path": "/qyZ8YH4d5wJdzKnnBOpMfSCrNVF.jpg",
      "season_number": 4
    }
  ],
  "status": "Ended",
  "type": "Scripted",
  "vote_average": 7.1,
  "vote_count": 56
}