{
  "Id": "tt15789038",
  "Title": "Elemental",
  "FullTitle": "Elemental (2023)",
  "Type": "Movie",
  "Year": "2023",
  "Image": "https://m.media-amazon.com/images/M/MV5BNjU2MjE1OGItZjdmYS00ZmIyLTljNjYtOWI5ZGRkZjM4NDEwXkEyXkFqcGc@._V1_.jpg",
  "ReleaseDate": "2023-06-16",
  "RuntimeMins": "101",
  "RuntimeStr": "1h 41min",
  "Plot": "Follow Ember and Wade, in a city where fire, water, earth and air live together.",
  "PlotLocalIsRtl": false,
  "Directors": "Peter Sohn",
  "DirectorList": [
    {
      "Id": "nm0812307",
      "Name": "Peter Sohn"
    }
  ],
  "Writers": "John Hoberg, Kat Likkel, Brenda Hsueh",
  "WriterList": [
    {
      "Id": "nm0387671",
      "Name": "John Hoberg"
    },
    {
      "Id": "nm0969581",
      "Name": "Kat Likkel"
    },
    {
      "Id": "nm1597674",
      "Name": "Brenda Hsueh"
    }
  ],
  "Stars": "Leah Lewis, Mamoudou Athie, Ronnie Del Carmen",
  "StarList": [
    {
      "Id": "nm2301427",
      "Name": "Leah Lewis"
    },
    {
      "Id": "nm6974206",
      "Name": "Mamoudou Athie"
    },
    {
      "Id": "nm0215455",
      "Name": "Ronnie Del Carmen"
    }
  ],
  "ActorList": [
    {
      "Id": "nm2301427",
      "Image": "",
      "Name": "Leah Lewis",
      "AsCharacter": ""
    },
    {
      "Id": "nm6974206",
      "Image": "",
      "Name": "Mamoudou Athie",
      "AsCharacter": ""
    },
    {
      "Id": "nm0215455",
      "Image": "",
      "Name": "Ronnie Del Carmen",
      "AsCharacter": ""
    }
  ],
  "FullCast": {
    "IMDbId": "tt15789038",
    "Title": "Elemental",
    "FullTitle": "Elemental (2023)",
    "Type": "Movie",
    "Year": "2023",
    "ErrorMessage": "",
    "Directors": {
      "Job": "Director",
      "Items": []
    },
    "Writers": {
      "Job": "Writer",
      "Items": []
    },
    "Actors": [],
    "Others": []
  },
  "Genres": "Animation, Adventure, Comedy",
  "GenreList": [
    {
      "Key": "Animation",
      "Value": "Animation"
    },
    {
      "Key": "Adventure",
      "Value": "Adventure"
    },
    {
      "Key": "Comedy",
      "Value": "Comedy"
    }
  ],
  "Companies": "Production companies, Walt Disney Pictures, Pixar Animation Studios, Hurwitz Creative",
  "CompanyList": [
    {
      "Name": "Production companies"
    },
    {
      "Id": "co0008970",
      "Name": "Walt Disney Pictures"
    },
    {
      "Id": "co0017902",
      "Name": "Pixar Animation Studios"
    },
    {
      "Id": "co0041001",
      "Name": "Hurwitz Creative"
    }
  ],
  "Countries": "United States",
  "CountryList": [
    {
      "Key": "United States",
      "Value": "United States"
    }
  ],
  "Languages": "English",
  "LanguageList": [
    {
      "Key": "English",
      "Value": "English"
    }
  ],
  "ContentRating": "PG",
  "IMDbRating": "7",
  "IMDbRatingVotes": "163639",
  "MetacriticRating": "58",
  "Ratings": {},
  "Wikipedia": {
    "PlotShort": {
      "PlainText": "",
      "Html": ""
    },
    "PlotFull": {
      "PlainText": "",
      "Html": ""
    }
  },
  "Posters": {
    "Posters": [],
    "Backdrops": []
  },
  "Images": {
    "Items": []
  },
  "Trailer": {},
  "BoxOffice": {
    "Budget": "",
    "OpeningWeekendUSA": "",
    "GrossUSA": "",
    "CumulativeWorldwideGross": ""
  },
  "Keywords": "3d animation,pixar,cgi animation,interracial relationship,interracial romance",
  "KeywordList": [
    "3d animation",
    "pixar",
    "cgi animation",
    "interracial relationship",
    "interracial romance"
  ],
  "Similars": [],
  "TvSeriesInfo": {
    "YearEnd": "",
    "Creators": "",
    "CreatorList": [],
    "Seasons": []
  },
  "TvEpisodeInfo": {}
}